doipy/__init__.py
doipy/__main__.py
doipy/actions/__init__.py
doipy/actions/cordra.py
doipy/actions/doip.py
doipy/actions/fdo_config_type_14.py
doipy/actions/fdo_manager.py
doipy/constants.py
doipy/dtr_utils.py
doipy/exceptions.py
doipy/get_objects_from_apis.py
doipy/main.py
doipy/models.py
doipy/request_and_response.py
doipy/validation_utils.py
doipy-1.0.0.dist-info/METADATA
doipy-1.0.0.dist-info/WHEEL
doipy-1.0.0.dist-info/entry_points.txt
doipy-1.0.0.dist-info/RECORD
