Metadata-Version: 2.1
Name: doipy
Version: 1.0.0
Summary: A Python wrapper for DOIP.
Author: Triet Doan
Author-email: triet.doan@gwdg.de
Requires-Python: >=3.11,<4.0
Classifier: Development Status :: 3 - Alpha
Classifier: Environment :: Console
Classifier: Programming Language :: Python :: 3
Classifier: Programming Language :: Python :: 3.11
Classifier: Programming Language :: Python :: 3.12
Classifier: Topic :: Software Development :: Libraries :: Python Modules
Requires-Dist: doip-sdk (>=0.0.6,<0.0.7)
Requires-Dist: jsonschema (>=4.22.0,<5.0.0)
Requires-Dist: pydantic (>=2.6.3,<3.0.0)
Requires-Dist: pydantic-settings (>=2.2.1,<3.0.0)
Requires-Dist: python-benedict[parse] (>=0.33.2,<0.34.0)
Requires-Dist: requests (>=2.32.3,<3.0.0)
Requires-Dist: rich (>=13.7.0,<14.0.0)
Requires-Dist: typer[all] (>=0.9.0,<0.10.0)
